README.rst
setup.py
gui_components/__init__.py
gui_components/encode_tab_gui.py
gui_components/extract_tab_gui.py
gui_components/instructions_tab_gui.py
gui_components/shared_gui_resources.py
gui_components/status_box.py
src/__init__.py
src/blowfish.py
src/steganopy.py
steganopy/__init__.py
steganopy/api.py
steganopy/gui.py
steganopy.egg-info/PKG-INFO
steganopy.egg-info/SOURCES.txt
steganopy.egg-info/dependency_links.txt
steganopy.egg-info/entry_points.txt
steganopy.egg-info/not-zip-safe
steganopy.egg-info/requires.txt
steganopy.egg-info/top_level.txt