Metadata-Version: 1.1
Name: steganopy
Version: 0.0.1
Summary: A steganography tool written in Python
Home-page: http://github.com/JarrodCTaylor/steganopy
Author: Jarrod C. Taylor
Author-email: jarrod.c.taylor@gmail.com
License: MIT
Platform: UNKNOWN
Classifier: Topic :: Security
Classifier: Topic :: Security :: Cryptography
Classifier: Intended Audience :: Developers
Classifier: Intended Audience :: End Users/Desktop
Classifier: Topic :: Software Development :: Libraries
